stegpng/__init__.py
stegpng/chunks.py
stegpng/png.py
stegpng/pngexceptions.py
stegpng-1.0.0b4.dist-info/DESCRIPTION.rst
stegpng-1.0.0b4.dist-info/METADATA
stegpng-1.0.0b4.dist-info/RECORD
stegpng-1.0.0b4.dist-info/WHEEL
stegpng-1.0.0b4.dist-info/metadata.json
stegpng-1.0.0b4.dist-info/top_level.txt
